ankilist.py
ankilist-0.1.6.dist-info/entry_points.txt
ankilist-0.1.6.dist-info/WHEEL
ankilist-0.1.6.dist-info/METADATA
ankilist-0.1.6.dist-info/RECORD
