Metadata-Version: 2.1
Name: ankilist
Version: 0.1.6
Summary: Lite google translate console client and anki list generator
License: GPL-3.0-or-later
Author: VladislavNekto
Author-email: vladislav.nekto.dev@gmail.com
Requires-Python: ==3.7.4
Classifier: License :: OSI Approved :: GNU General Public License v3 or later (GPLv3+)
Classifier: Programming Language :: Python :: 3
